subset2evaluate/__init__.py
subset2evaluate/evaluate.py
subset2evaluate/methods.py
subset2evaluate/methods_old.py
subset2evaluate/reference_info.py
subset2evaluate/select_subset.py
subset2evaluate/test.py
subset2evaluate/utils.py
subset2evaluate-1.0.22.dist-info/METADATA
subset2evaluate-1.0.22.dist-info/WHEEL
subset2evaluate-1.0.22.dist-info/entry_points.txt
subset2evaluate-1.0.22.dist-info/top_level.txt
subset2evaluate-1.0.22.dist-info/RECORD
