Metadata-Version: 2.4
Name: subset2evaluate
Version: 1.0.22
Summary: Find informative examples to efficiently (human-)evaluate NLG models.
Author-email: Vilém Zouhar <vilem.zouhar@gmail.com>
License: MIT
Project-URL: Repository, https://github.com/zouharvi/subset2evaluate
Project-URL: Issues, https://github.com/zouharvi/subset2evaluate/issues
Keywords: evaluation,natural language generation,machine translation,human evaluation,subset selection
Classifier: Environment :: Console
Classifier: Intended Audience :: Science/Research
Classifier: Topic :: Scientific/Engineering :: Artificial Intelligence
Requires-Python: >=3.11
Requires-Dist: numpy
Requires-Dist: pandas
Requires-Dist: sacrebleu
Requires-Dist: datasets
Requires-Dist: scikit-learn
Requires-Dist: tqdm
Requires-Dist: matplotlib
Requires-Dist: requests
Requires-Dist: sentence-transformers
